PiKit/__init__.py
PiKit/add_num.py
PiKit/cvkit.py
PiKit/face_detetion.py
openpicv/__init__.py
openpicv/add_num.py
openpicv/cvkit.py
openpicv/face_detetion.py
openpicv /__init__.py
openpicv /add_num.py
openpicv /cvkit.py
openpicv /face_detetion.py
openpicv-test/__init__.py
openpicv-test/add_num.py
openpicv-test/face_detetion.py
openpicv-1.1.7.dist-info/LICENSE
openpicv-1.1.7.dist-info/METADATA
openpicv-1.1.7.dist-info/WHEEL
openpicv-1.1.7.dist-info/top_level.txt
openpicv-1.1.7.dist-info/RECORD
