Metadata-Version: 2.1
Name: openpicv
Version: 1.1.7
Summary: 一个非常NB的包
Author: coder_zqs
Author-email: wupeiqi@163.com
Classifier: Programming Language :: Python :: 3
Classifier: License :: OSI Approved :: MIT License
Classifier: Operating System :: OS Independent
Requires-Python: >=3
License-File: LICENSE
Requires-Dist: opencv-python
